setup.cfg
setup.py
kinetic_scales/__init__.py
kinetic_scales.egg-info/PKG-INFO
kinetic_scales.egg-info/SOURCES.txt
kinetic_scales.egg-info/dependency_links.txt
kinetic_scales.egg-info/top_level.txt
kinetic_scales/function/__init__.py
kinetic_scales/function/exponential.py
kinetic_scales/function/hyperbolic.py
kinetic_scales/function/linear.py
kinetic_scales/weighted/__init__.py
kinetic_scales/weighted/integer.py
kinetic_scales/weighted/rank.py