Metadata-Version: 1.1
Name: kinetic-scales
Version: 1.0.2
Summary: A library with some selection and weighted choice algorithms.
Home-page: https://github.com/RealKinetic/scales
Author: Real Kinetic
Author-email: dev@realkinetic.com
License: UNKNOWN
Download-URL: https://github.com/RealKinetic/scales/archive/v1.0.2.tar.gz
Keywords: weighted,random,choice
Platform: UNKNOWN
